pysigrok_xspiflash.py
pysigrok_decoder_xspiflash-0.0.1.dist-info/entry_points.txt
pysigrok_decoder_xspiflash-0.0.1.dist-info/LICENSE
pysigrok_decoder_xspiflash-0.0.1.dist-info/WHEEL
pysigrok_decoder_xspiflash-0.0.1.dist-info/METADATA
pysigrok_decoder_xspiflash-0.0.1.dist-info/RECORD
