Metadata-Version: 2.1
Name: pysigrok-decoder-xspiflash
Version: 0.0.1
Summary: PySigrok decoder for multibit SPI flash transactions.
Author-email: Scott Shawcroft <scott@tannewt.org>
Requires-Python: >=3.7
Classifier: License :: OSI Approved :: MIT License
Requires-Dist: pysigrok >= 0.4.0
Project-URL: Home, https://github.com/pysigrok/decoder-xspiflash
